LICENSE
MANIFEST.in
README.md
VERSION
requirements.txt
setup.py
masearch/__init__.py
masearch/masearch.py
masearch.egg-info/PKG-INFO
masearch.egg-info/SOURCES.txt
masearch.egg-info/dependency_links.txt
masearch.egg-info/requires.txt
masearch.egg-info/top_level.txt