Metadata-Version: 2.1
Name: masearch
Version: 0.0.1
Summary: Monotonic Alignment Search
Home-page: https://github.com/pengzhendong/masearch
Author: Zhendong Peng
Author-email: pzd17@tsinghua.org.cn
Classifier: Programming Language :: Python :: 3
Classifier: Operating System :: OS Independent
Classifier: Topic :: Scientific/Engineering
License-File: LICENSE
